<Properties StartupConfiguration="{9C3EB822-419E-4E2A-8B33-BE822F3CDFFB}|Default">
  <MonoDevelop.Ide.Workbench ActiveDocument="GameLogic.cs">
    <Files>
      <File FileName="Program.cs" Line="12" Column="44" />
      <File FileName="PlayerInput.cs" />
      <File FileName="GameLogic.cs" Line="12" Column="10" />
      <File FileName="GameGrid.cs" />
    </Files>
  </MonoDevelop.Ide.Workbench>
  <MonoDevelop.Ide.DebuggingService.PinnedWatches />
  <MonoDevelop.Ide.Workspace ActiveConfiguration="Debug" />
  <MonoDevelop.Ide.DebuggingService.Breakpoints>
    <BreakpointStore />
  </MonoDevelop.Ide.DebuggingService.Breakpoints>
  <MultiItemStartupConfigurations />
  <MonoDevelop.Ide.ItemProperties.BattleShip PreferredExecutionTarget="MonoDevelop.Default" />
</Properties>